pandoc/__init__.py
pandoc/__main__.py
pandoc/about.py
pandoc/pandoc-types.js
pandoc/tests.md
pandoc/tests.py
pandoc/types.py
pandoc/utils.py
pandoc/doctest/__init__.py
pandoc-1.1.0.dist-info/METADATA
pandoc-1.1.0.dist-info/WHEEL
pandoc-1.1.0.dist-info/top_level.txt
pandoc-1.1.0.dist-info/RECORD
