Metadata-Version: 2.1
Name: pandoc
Version: 1.1.0
Summary: Pandoc Documents for Python
Home-page: https://github.com/boisgera/pandoc
Author: Sébastien Boisgérault
Author-email: Sebastien.Boisgerault@mines-paristech.fr
License: MIT License
Platform: UNKNOWN
Classifier: Development Status :: 5 - Production/Stable
Classifier: Programming Language :: Python :: 2.7
Classifier: Topic :: Software Development
Classifier: Topic :: Text Processing
Requires-Dist: plumbum
Requires-Dist: ply
